MANIFEST.in
README
setup.py
fshttpstream/__init__.py
fshttpstream/client.py
fshttpstream/queueinboundsocket.py
fshttpstream/server.py
fshttpstream/stderr2log.py
fshttpstream/websocketserver.py
fshttpstream.egg-info/PKG-INFO
fshttpstream.egg-info/SOURCES.txt
fshttpstream.egg-info/dependency_links.txt
fshttpstream.egg-info/not-zip-safe
fshttpstream.egg-info/requires.txt
fshttpstream.egg-info/top_level.txt
fshttpstream/examples/INSTALL
fshttpstream/examples/fshttpstream.js
fshttpstream/examples/jquery.fshttpstream.js
fshttpstream/examples/jquerytest.html
fshttpstream/examples/myserver.py
fshttpstream/examples/test.html
fshttpstream/javascript/fshttpstream.js
fshttpstream/javascript/jquery.fshttpstream.js