Metadata-Version: 1.0
Name: fshttpstream
Version: 0.3.2
Summary: Websocket proxy server to send freeswitch events to websocket client.
Home-page: http://github.com/tamiel/fshttpstream
Author: Michael Ricordeau
Author-email: michael.ricordeau@gmail.com
License: MPL 1.1
Platform: linux
Classifier: License :: OSI Approved :: Mozilla Public License 1.1 (MPL 1.1)
Classifier: Programming Language :: Python
Classifier: Operating System :: POSIX
Classifier: Topic :: Internet
Classifier: Topic :: Software Development :: Libraries :: Python Modules
Classifier: Topic :: Communications
Classifier: Topic :: Multimedia
Classifier: Environment :: Web Environment
Classifier: Programming Language :: JavaScript
Classifier: Intended Audience :: Developers
Classifier: Intended Audience :: Telecommunications Industry
Classifier: Development Status :: 4 - Beta
